Metadata-Version: 1.1
Name: tiddlywebplugins.static
Version: 1.2.0
Summary: A TiddlyWeb plugin that handles delivery of static files over HTTP.
Home-page: http://pypi.python.org/pypi/tiddlywebplugins.static
Author: Chris Dent
Author-email: cdent@peermore.com
License: UNKNOWN
Platform: Posix; MacOS X; Windows
Classifier: Environment :: Web Environment
Classifier: License :: OSI Approved :: BSD License
Classifier: Operating System :: OS Independent
Classifier: Programming Language :: Python :: 2.7
Classifier: Programming Language :: Python :: 3.3
Classifier: Topic :: Internet :: WWW/HTTP :: WSGI :: Application
